MANIFEST.in
Makefile
README
setup.py
tiddlywebplugins/__init__.py
tiddlywebplugins/wimporter.py
tiddlywebplugins.wimporter.egg-info/PKG-INFO
tiddlywebplugins.wimporter.egg-info/SOURCES.txt
tiddlywebplugins.wimporter.egg-info/dependency_links.txt
tiddlywebplugins.wimporter.egg-info/namespace_packages.txt
tiddlywebplugins.wimporter.egg-info/not-zip-safe
tiddlywebplugins.wimporter.egg-info/requires.txt
tiddlywebplugins.wimporter.egg-info/top_level.txt
tiddlywebplugins/templates/chooser.html
tiddlywebplugins/templates/wimport.html