Metadata-Version: 1.0
Name: tiddlywebplugins.wimporter
Version: 0.9.4
Summary: A TiddlyWeb plugin for server side import of tiddlers.
Home-page: http://pypi.python.org/pypi/tiddlywebplugins.wimporter
Author: Chris Dent
Author-email: cdent@peermore.com
License: UNKNOWN
Platform: Posix; MacOS X; Windows
